{
"type": "FeatureCollection",
"name": "PERIBADATAN",
"crs": { "type": "name", "properties": { "name": "urn:ogc:def:crs:OGC:1.3:CRS84" } },
"features": [
{ "type": "Feature", "properties": { "NAMA": "masjid baitul izzah", "JENIS": " Masjid", "RATING": "3,5", "REVIEW": "(6)", "ALAMAT": "F65V+3MQ", "KECAMATAN": "Magelang Utara", "Full Address": "masjid baitul izzah F65V+3MQ Magelang Utara ", "Latitude": -7.5422751, "Longitude": 110.2442324 }, "geometry": { "type": "Point", "coordinates": [ 110.2442324, -7.5422751 ] } }
]
}
